Metadata-Version: 2.4
Name: adafruit-circuitpython-anchored-tilegrid
Version: 1.0.2
Summary: TileGrid subclass that can be placed relative to an arbitrary anchor point.
Author-email: Adafruit Industries <circuitpython@adafruit.com>
License: MIT
Project-URL: Homepage, https://github.com/adafruit/Adafruit_CircuitPython_Anchored_TileGrid
Keywords: adafruit,blinka,circuitpython,micropython,anchored_tilegrid,displayio,tilegrid,position,anchor,anchor_point,anchored_position
Classifier: Intended Audience :: Developers
Classifier: Topic :: Software Development :: Libraries
Classifier: Topic :: Software Development :: Embedded Systems
Classifier: Topic :: System :: Hardware
Classifier: License :: OSI Approved :: MIT License
Classifier: Programming Language :: Python :: 3
License-File: LICENSE
Requires-Dist: Adafruit-Blinka
Requires-Dist: Adafruit-Blinka-Displayio
Provides-Extra: optional
Dynamic: license-file
